README.txt
setup.py
lifepim/__init__.py
lifepim/lifepim.py
lifepim.egg-info/PKG-INFO
lifepim.egg-info/SOURCES.txt
lifepim.egg-info/dependency_links.txt
lifepim.egg-info/requires.txt
lifepim.egg-info/top_level.txt
lifepim/web_app/__init__.py