Metadata-Version: 1.1
Name: lifepim
Version: 0.0.2
Summary: Personal Information Manager for Life
Home-page: https://github.com/acutesoftware/lifepim
Author: Duncan Murray
Author-email: djmurray@acutesoftware.com.au
License: GNU General Public License v3 (GPLv3)
Platform: UNKNOWN
Classifier: Development Status :: 1 - Planning
Classifier: Environment :: Web Environment
Classifier: Programming Language :: Python :: 3
Classifier: Programming Language :: Python :: 3.4
Classifier: Intended Audience :: Developers
Classifier: Natural Language :: English
Classifier: Operating System :: OS Independent
Classifier: Topic :: Software Development :: Libraries :: Application Frameworks
Classifier: Topic :: Software Development :: Libraries :: Python Modules
Classifier: Topic :: Office/Business :: News/Diary
